llmdo
