Metadata-Version: 2.1
Name: llmdo
Version: 0.2.1
Summary: Ask GPT to run a command
Author-email: David Li <david@david-li.com>
License: GPL-3.0
Keywords: llm,gpt,cli
Requires-Python: >=3.8
License-File: LICENSE
Requires-Dist: openai>=1.30.5
Requires-Dist: anthropic
Provides-Extra: dev
Requires-Dist: build; extra == "dev"
Requires-Dist: twine; extra == "dev"
